README.rst
setup.cfg
setup.py
Apilisk.egg-info/PKG-INFO
Apilisk.egg-info/SOURCES.txt
Apilisk.egg-info/dependency_links.txt
Apilisk.egg-info/entry_points.txt
Apilisk.egg-info/requires.txt
Apilisk.egg-info/top_level.txt
apilisk/__init__.py
apilisk/apiwatcher_client.py
apilisk/command_line.py
apilisk/curl_caller.py
apilisk/exceptions.py
apilisk/junit_formatter.py
apilisk/printer.py
apilisk/runner.py
apilisk/utils.py