Metadata-Version: 1.1
Name: Apilisk
Version: 0.1.2
Summary: Remote test runner for Apiwatcher platform
Home-page: https://github.com/apiwatcher/apilisk
Author: Karel Jakubec
Author-email: karel@jakubec.name
License: MIT
Keywords: http client apiwatcher apilisk
Platform: UNKNOWN
Classifier: Development Status :: 3 - Alpha
Classifier: Intended Audience :: Developers
Classifier: Environment :: Console
Classifier: Natural Language :: English
Classifier: Operating System :: OS Independent
Classifier: License :: OSI Approved :: MIT License
Classifier: Programming Language :: Python :: 2
Classifier: Programming Language :: Python :: 2.7
Classifier: Topic :: System :: Networking :: Monitoring
